LICENSE
MANIFEST.in
README.txt
setup.py
ejemplos/ejemplo.py
ejemplos/enciende-apaga.py
ejemplos/medidor_distancia.py
ejemplos/pulsador.py
ejemplos/semaforo4_gui_phi2.py
ejemplos/teclasymotores.py
ejemplos/variador_velocidad.py
modulo_arduino/leer.txt
modulo_arduino/phi2.ino
phi2/__init__.py
phi2/phi2.py
phi2.egg-info/PKG-INFO
phi2.egg-info/SOURCES.txt
phi2.egg-info/dependency_links.txt
phi2.egg-info/requires.txt
phi2.egg-info/top_level.txt